euclides/__init__.py
euclides/euclidesproto_pb2.py
euclides/euclidesproto_pb2_grpc.py
euclides/services.py
euclides-0.2.0.dist-info/METADATA
euclides-0.2.0.dist-info/WHEEL
euclides-0.2.0.dist-info/top_level.txt
euclides-0.2.0.dist-info/RECORD
