Metadata-Version: 2.1
Name: euclides
Version: 0.2.0
Summary: EuclidesDB Python client API.
Home-page: https://github.com/perone/euclidesdb
Author: Christian S. Perone
Author-email: christian.perone@gmail.com
License: UNKNOWN
Platform: UNKNOWN
Classifier: Development Status :: 3 - Alpha
Classifier: Intended Audience :: Developers
Classifier: Programming Language :: Python :: 3
Requires-Dist: Pillow (>=5.3.0)
Requires-Dist: grpcio (>=1.15.0)
Requires-Dist: grpcio-tools (>=1.15.0)
Requires-Dist: protobuf (>=3.6.1)
